whitepyges/__init__.py
whitepyges/address.py
whitepyges/config.py
whitepyges/helper.py
whitepyges/person.py
whitepyges/phone.py
whitepyges-0.5b0.dist-info/licenses/LICENSE
whitepyges-0.5b0.dist-info/licenses/NOTICE
whitepyges-0.5b0.dist-info/METADATA
whitepyges-0.5b0.dist-info/WHEEL
whitepyges-0.5b0.dist-info/top_level.txt
whitepyges-0.5b0.dist-info/RECORD
