Metadata-Version: 2.4
Name: whitepyges
Version: 0.5b0
Summary: Unofficial Python client for Whitepages
Author-email: Will Hellinger <111201130+Will-Hellinger@users.noreply.github.com>
License: MIT
Project-URL: Homepage, https://github.com/Will-Hellinger/whitepyges
Project-URL: Documentation, https://will-hellinger.github.io/whitepyges/
Project-URL: Source, https://github.com/Will-Hellinger/whitepyges
Project-URL: Tracker, https://github.com/Will-Hellinger/whitepyges/issues
Classifier: Programming Language :: Python :: 3
Classifier: License :: OSI Approved :: MIT License
Classifier: Operating System :: OS Independent
Requires-Python: >=3.9
License-File: LICENSE
License-File: NOTICE
Requires-Dist: beautifulsoup4==4.13.3
Requires-Dist: cloudscraper==1.2.71
Requires-Dist: requests==2.32.3
Provides-Extra: dev
Requires-Dist: pytest; extra == "dev"
Requires-Dist: coverage; extra == "dev"
Requires-Dist: black; extra == "dev"
Provides-Extra: docs
Requires-Dist: mkdocs; extra == "docs"
Requires-Dist: mkdocs-material; extra == "docs"
Requires-Dist: mkdocstrings; extra == "docs"
Requires-Dist: mkdocstrings-python; extra == "docs"
Requires-Dist: mkdocs-minify-plugin; extra == "docs"
Requires-Dist: mkdocs-git-revision-date-localized-plugin; extra == "docs"
Requires-Dist: mkdocs-coverage; extra == "docs"
Requires-Dist: pymdown-extensions; extra == "docs"
Dynamic: license-file
